komodo_cli/__init__.py
komodo_cli/cli.py
komodo_cli/printing.py
komodo_cli/types.py
komodo_cli/utils.py
komodo_cli/version.py
komodo_cli/commands/__init__.py
komodo_cli/commands/cmd_cancel.py
komodo_cli/commands/cmd_delete.py
komodo_cli/commands/cmd_do.py
komodo_cli/commands/cmd_list.py
komodo_cli/commands/cmd_logs.py
komodo_cli/commands/cmd_register.py
komodo_cli/commands/cmd_run.py
komodo_cli/commands/cmd_shell.py
komodo_cli/commands/cmd_status.py
komodo_cli/overlay_images/__init__.py
komodo_cli/overlay_images/overlay_images.py
komodo_cli-0.0.4.dist-info/LICENSE
komodo_cli-0.0.4.dist-info/METADATA
komodo_cli-0.0.4.dist-info/WHEEL
komodo_cli-0.0.4.dist-info/entry_points.txt
komodo_cli-0.0.4.dist-info/top_level.txt
komodo_cli-0.0.4.dist-info/RECORD
