Metadata-Version: 2.1
Name: komodo-cli
Version: 0.0.4
Summary: A CLI client for Komodo AI
Home-page: https://github.com/kmushegi/puma_cli
Author: kmushegi
Author-email: mushegiani@gmail.com
License: UNKNOWN
Download-URL: https://github.com/kmushegi/puma_cli/archive/0.0.4.tar.gz
Platform: UNKNOWN
Classifier: Topic :: Software Development :: Libraries
Classifier: License :: OSI Approved :: Apache Software License
Classifier: Programming Language :: Python :: 3.8
Classifier: Operating System :: OS Independent
Requires-Python: >=3
Requires-Dist: click
